rhvoice_wrapper_bin-0.5.0.data/purelib/rhvoice_wrapper_bin/__init__.py
rhvoice_wrapper_bin-0.5.0.data/purelib/rhvoice_wrapper_bin/lib/RHVoice.dll
rhvoice_wrapper_bin-0.5.0.dist-info/LICENSE.md
rhvoice_wrapper_bin-0.5.0.dist-info/METADATA
rhvoice_wrapper_bin-0.5.0.dist-info/WHEEL
rhvoice_wrapper_bin-0.5.0.dist-info/top_level.txt
rhvoice_wrapper_bin-0.5.0.dist-info/RECORD
