Metadata-Version: 2.1
Name: rhvoice-wrapper-bin
Version: 0.5.0
Summary: Provides RHVoice libraries for rhvoice-wrapper
Home-page: https://github.com/Aculeasis/rhvoice-wrapper-bin
Author: Aculeasis
Author-email: amilpalimov2@ya.ru
License: GPLv3+
Classifier: Intended Audience :: Developers
Classifier: Programming Language :: Python :: 3
Classifier: Programming Language :: C++
Classifier: License :: OSI Approved :: GNU General Public License v3 or later (GPLv3+)
Classifier: Operating System :: POSIX :: Linux
Classifier: Operating System :: Microsoft :: Windows
Classifier: Topic :: Multimedia :: Sound/Audio :: Speech
Classifier: Topic :: Software Development :: Libraries
Requires-Python: >=3.4
License-File: LICENSE.md
Requires-Dist: rhvoice-wrapper-data~=0.5.0
